shoutcast_api/Exceptions.py
shoutcast_api/__init__.py
shoutcast_api/genres.py
shoutcast_api/models.py
shoutcast_api/shoutcast_request.py
shoutcast_api/stations.py
shoutcast_api/tunein.py
shoutcast_api/utils.py
tests/__init__.py
tests/base.py
tests/test_genres.py
tests/test_stations.py
tests/test_tunein.py
shoutcast_api-1.0.8.dist-info/LICENSE
shoutcast_api-1.0.8.dist-info/METADATA
shoutcast_api-1.0.8.dist-info/WHEEL
shoutcast_api-1.0.8.dist-info/top_level.txt
shoutcast_api-1.0.8.dist-info/RECORD
