Metadata-Version: 2.1
Name: shoutcast-api
Version: 1.0.8
Summary: Shoutcast Radio Directory API 
Home-page: https://github.com/eadwinCode/shoutcast_api
Author: eadwinCode
Author-email: ezeudoh.tochukwu@gmail.com
License: MIT
Keywords: shoutcast radio api
Platform: UNKNOWN
Classifier: Development Status :: 5 - Production/Stable
Classifier: Programming Language :: Python :: 3
Classifier: License :: OSI Approved :: MIT License
Classifier: Operating System :: OS Independent
Classifier: Topic :: Internet :: WWW/HTTP
Requires-Dist: requests (==2.23.0)
Requires-Dist: xmltodict (==0.12.0)
